README.md
setup.py
module_discovery_utils/__init__.py
module_discovery_utils/module_discovery_utils.py
module_discovery_utils.egg-info/PKG-INFO
module_discovery_utils.egg-info/SOURCES.txt
module_discovery_utils.egg-info/dependency_links.txt
module_discovery_utils.egg-info/top_level.txt
test/test_bad_inputs.py
test/test_instance_discovery.py
test/test_module_loading.py
test/test_subclass_discovery.py