Metadata-Version: 2.1
Name: module-discovery-utils
Version: 1.0.1
Summary: A simple library to allow easy package/module level introspection
Home-page: https://github.com/zsennenga/module-discovery-utils
Author: Zach Ennenga
Author-email: astrozees@gmail.com
License: Apache License 2.0
Platform: UNKNOWN
